OTCFinUtils/__init__.py
OTCFinUtils/buffer.py
OTCFinUtils/data_structs.py
OTCFinUtils/dataverse_handler.py
OTCFinUtils/mapper.py
OTCFinUtils/mapper_loading.py
OTCFinUtils/security.py
OTCFinUtils/sharepoint.py
OTCFinUtils/sharepoint_client.py
OTCFinUtils/utils.py
otcfinutils-0.0.24.20.dist-info/METADATA
otcfinutils-0.0.24.20.dist-info/WHEEL
otcfinutils-0.0.24.20.dist-info/top_level.txt
otcfinutils-0.0.24.20.dist-info/RECORD
