Metadata-Version: 2.4
Name: otcfinutils
Version: 0.0.24.20
Summary: Useful functions to interact with dataverse and sharepoint
Author: Petar Kasapinov, Shomoos Aldujaily
Author-email: pkasapinov@otcfin.com, saldujaily@otcfin.com
Requires-Dist: msal
Requires-Dist: python-dotenv
Requires-Dist: pandas
Requires-Dist: azure-identity
Requires-Dist: azure-keyvault-secrets
Requires-Dist: openpyxl
Dynamic: author
Dynamic: author-email
Dynamic: requires-dist
Dynamic: summary
